spacs/__init__.py
spacs/client.py
spacs/conf.py
spacs-0.0.9.dist-info/LICENSE
spacs-0.0.9.dist-info/METADATA
spacs-0.0.9.dist-info/WHEEL
spacs-0.0.9.dist-info/RECORD
