Metadata-Version: 2.1
Name: spacs
Version: 0.0.9
Summary: Simple Pydantic AIOHTTP Client Sessions
Home-page: https://github.com/rlebel12/spacs
Author: rlebel12
Requires-Python: >=3.11,<4.0
Classifier: Programming Language :: Python :: 3
Classifier: Programming Language :: Python :: 3.11
Requires-Dist: aiohttp (>=3.8.4,<4.0.0)
Requires-Dist: pydantic (>=1.10.7,<2.0.0)
Project-URL: Repository, https://github.com/rlebel12/spacs
